setup.py
nots/__init__.py
nots/converters.py
nots/exceptions.py
nots/serializer.py
nots.egg-info/PKG-INFO
nots.egg-info/SOURCES.txt
nots.egg-info/dependency_links.txt
nots.egg-info/top_level.txt
playground/__init__.py
playground/play.py