Metadata-Version: 1.1
Name: nots
Version: 0.0.1
Summary: Not obviously traditional serialization.
Home-page: UNKNOWN
Author: Stan Prokop
Author-email: UNKNOWN
License: Apache License, version 2.0
Keywords: serialization deserialization json
Platform: UNKNOWN
Classifier: Development Status :: 4 - Beta
Classifier: Intended Audience :: Developers
Classifier: Topic :: Software Development :: Libraries
Classifier: License :: OSI Approved :: MIT License
Classifier: Programming Language :: Python :: 3.6
